get_music/__init__.py
get_music/download.py
get_music/downloads.py
get_music/get_music.py
get_music/gui.py
get_music/playerlist.py
get_music/top.py
get_music/ver.py
get_music/api/__init__.py
get_music/api/baidu.py
get_music/api/fivesing.py
get_music/api/kugou.py
get_music/api/kuwo.py
get_music/api/migu.py
get_music/api/netease.py
get_music/api/oneting.py
get_music/api/qq.py
get_music/api/singbz.py
get_music/api/zhidao.py
get_music/api_list/__init__.py
get_music/api_list/kg_one_playerlist.py
get_music/api_list/kg_playerlist.py
get_music/api_list/kw_playerlist.py
get_music/api_list/qq_playerlist.py
get_music/api_list/wy_playerlist.py
get_music_lizhanqi-1.2.14.dist-info/LICENSE.txt
get_music_lizhanqi-1.2.14.dist-info/METADATA
get_music_lizhanqi-1.2.14.dist-info/WHEEL
get_music_lizhanqi-1.2.14.dist-info/entry_points.txt
get_music_lizhanqi-1.2.14.dist-info/top_level.txt
get_music_lizhanqi-1.2.14.dist-info/RECORD
