Metadata-Version: 2.1
Name: get-music-lizhanqi
Version: 1.2.14
Summary: 可以下载音乐的包哦
Home-page: 
Author: Li Zhan Qi
Author-email: 3101978435@qq.com
Classifier: Programming Language :: Python :: 3
Classifier: License :: OSI Approved :: MIT License
Classifier: Operating System :: OS Independent
Requires-Python: >=3.7
License-File: LICENSE.txt
Requires-Dist: requests
Requires-Dist: rich
Requires-Dist: pycryptodome
